palletjack/__init__.py
palletjack/cpalletjack.pxd
palletjack/package_metadata.py
palletjack/palletjack.h
palletjack/palletjack_cython.cpython-314-darwin.so
palletjack/palletjack_cython.pyx
palletjack/parquet_types_palletjack.h
palletjack/windows_fixup.h
palletjack-2.9.0.dist-info/licenses/LICENSE
palletjack-2.9.0.dist-info/METADATA
palletjack-2.9.0.dist-info/WHEEL
palletjack-2.9.0.dist-info/top_level.txt
palletjack-2.9.0.dist-info/RECORD
