Metadata-Version: 2.4
Name: palletjack
Version: 2.9.0
Summary: Faster parquet metadata reading
Project-URL: Homepage, https://github.com/G-Research/PalletJack
Project-URL: Issues, https://github.com/G-Research/PalletJack/issues
Classifier: Programming Language :: Python :: 3
Classifier: License :: OSI Approved :: Apache Software License
Classifier: Operating System :: OS Independent
Requires-Python: >=3.9
License-File: LICENSE
Requires-Dist: pyarrow~=22.0.0
Dynamic: license-file
